pcaps/__init__.py
pcaps/admin.py
pcaps/apps.py
pcaps/models.py
pcaps/tests.py
pcaps/views.py
pcaps/migrations/0001_initial.py
pcaps/migrations/0002_initial.py
pcaps/migrations/0003_rename_rule_to_validate_pcap_rule_to_validate2_and_more.py
pcaps/migrations/0004_rename_rule_to_validate2_pcap_rule_to_validate_and_more.py
pcaps/migrations/__init__.py
settings/__init__.py
settings/admin.py
settings/apps.py
settings/models.py
settings/tests.py
settings/views.py
settings/migrations/0001_initial.py
settings/migrations/0002_remove_keywords_type_keywords_description_and_more.py
settings/migrations/0003_keywords_avalable.py
settings/migrations/0004_keyword_delete_keywords.py
settings/migrations/0005_remove_keyword_negation_alter_keyword_description_and_more.py
settings/migrations/0006_source.py
settings/migrations/__init__.py
snort/__init__.py
snort/admin.py
snort/apps.py
snort/models.py
snort/parser.py
snort/snort_templates.py
snort/tests.py
snort/views.py
snort/migrations/0001_initial.py
snort/migrations/0002_snortruleviewarray.py
snort/migrations/0003_snortruleviewarray_htmlid_and_more.py
snort/migrations/0004_snortrule_deleted.py
snort/migrations/0005_remove_snortrule_template_snortrule_is_template.py
snort/migrations/0006_rename_main_ref_snortrule_document_and_more.py
snort/migrations/0007_snortrule_tag.py
snort/migrations/0008_snortrule_exported_snortrule_sensitive.py
snort/migrations/0009_snortrule_source.py
snort/migrations/__init__.py
snort_web_master/__init__.py
snort_web_master/asgi.py
snort_web_master/settings.py
snort_web_master/urls.py
snort_web_master/wsgi.py
snort_web_master/middleware/__init__.py
snort_web_master/middleware/no_cache.py
snort_web_master-1.0.0.9.dist-info/LICENSE.rst
snort_web_master-1.0.0.9.dist-info/METADATA
snort_web_master-1.0.0.9.dist-info/WHEEL
snort_web_master-1.0.0.9.dist-info/top_level.txt
snort_web_master-1.0.0.9.dist-info/RECORD
